src/design/number_capture.sv
module number_capture (
    input  logic clk,
    input  logic rst_n,

    input  logic [3:0] key_code,
    input  logic       key_valid,

    input  logic       enable,      // NUEVO (controlado por FSM)

    output logic [9:0] number,
    output logic       done
);

    logic [1:0] digit_count;
    logic [9:0] temp_number;

    always_ff @(posedge clk or negedge rst_n) begin
        if (!rst_n) begin
            temp_number <= 0;
            digit_count <= 0;
            done <= 0;
        end else begin
            done <= 0;

            if (enable && key_valid && key_code <= 9) begin
                
                if (digit_count < 3) begin
                    temp_number <= (temp_number * 10) + key_code;
                    digit_count <= digit_count + 1;

                    if (digit_count == 2) begin
                        number <= (temp_number * 10) + key_code;
                        done <= 1;
                    end
                end
                // si ya hay 3 → ignora nuevas teclas
            end
        end
    end

endmodule

src/sim/number_capture_tb.sv
`timescale 1ns/1ps

module number_capture_tb;

    // Señales
    logic clk;
    logic rst_n;

    logic [3:0] key_code;
    logic key_valid;
    logic enable;

    logic [9:0] number;
    logic done;

    // DUT
    number_capture DUT (
        .clk(clk),
        .rst_n(rst_n),
        .key_code(key_code),
        .key_valid(key_valid),
        .enable(enable),
        .number(number),
        .done(done)
    );

    // Clock (periodo 20 ns)
    always #10 clk = ~clk;

    // Estímulos
    initial begin
        $dumpfile("number_capture.vcd");
        $dumpvars(0, number_capture_tb);

        clk = 0;
        rst_n = 0;
        key_code = 0;
        key_valid = 0;
        enable = 1;

        // Reset
        #50;
        rst_n = 1;

        // ---------------------------
        // Caso 1: 3 dígitos válidos (357)
        // ---------------------------
        send_key(4'd3);
        send_key(4'd5);
        send_key(4'd7);

        #50;

        // ---------------------------
        // Caso 2: cuarto dígito (debe ignorarse)
        // ---------------------------
        send_key(4'd9);

        #100;

        // ---------------------------
        // Caso 3: entradas no decimales (A, F)
        // ---------------------------
        send_key(4'hA);
        send_key(4'hF);

        #100;

        // ---------------------------
        // Caso 4: nuevo número (128)
        // ---------------------------
        rst_n = 0;
        #50;
        rst_n = 1;

        send_key(4'd1);
        send_key(4'd2);
        send_key(4'd8);

        #100;

        $finish;
    end

    // Tarea para simular pulsación de tecla
    task send_key(input [3:0] key);
        begin
            @(posedge clk);
            key_code  = key;
            key_valid = 1;

            @(posedge clk);
            key_valid = 0;

            // separación entre teclas
            repeat(5) @(posedge clk);
        end
    endtask

endmodule

src/build/number_capture.vcd
$date
	Sat Apr 25 22:08:09 2026
$end
$version
	Icarus Verilog
$end
$timescale
	1ps
$end
$scope module number_capture_tb $end
$var wire 10 ! number [9:0] $end
$var wire 1 " done $end
$var reg 1 # clk $end
$var reg 1 $ enable $end
$var reg 4 % key_code [3:0] $end
$var reg 1 & key_valid $end
$var reg 1 ' rst_n $end
$scope module DUT $end
$var wire 1 # clk $end
$var wire 1 $ enable $end
$var wire 4 ( key_code [3:0] $end
$var wire 1 & key_valid $end
$var wire 1 ' rst_n $end
$var reg 2 ) digit_count [1:0] $end
$var reg 1 " done $end
$var reg 10 * number [9:0] $end
$var reg 10 + temp_number [9:0] $end
$upscope $end
$scope task send_key $end
$var reg 4 , key [3:0] $end
$upscope $end
$upscope $end
$enddefinitions $end
$comment Show the parameter values. $end
$dumpall
$end
#0
$dumpvars
bx ,
b0 +
bx *
b0 )
b0 (
0'
0&
b0 %
1$
0#
0"
bx !
$end
#10000
1#
#20000
0#
#30000
1#
#40000
0#
#50000
b1 )
b11 +
1&
b11 %
b11 (
1#
b11 ,
1'
#60000
0#
#70000
0&
1#
#80000
0#
#90000
1#
#100000
0#
#110000
1#
#120000
0#
#130000
1#
#140000
0#
#150000
1#
#160000
0#
#170000
b101 ,
1#
#180000
0#
#190000
b10 )
b100011 +
1&
b101 %
b101 (
1#
#200000
0#
#210000
0&
1#
#220000
0#
#230000
1#
#240000
0#
#250000
1#
#260000
0#
#270000
1#
#280000
0#
#290000
1#
#300000
0#
#310000
b111 ,
1#
#320000
0#
#330000
1"
b101100101 !
b101100101 *
b11 )
b101100101 +
1&
b111 %
b111 (
1#
#340000
0#
#350000
0"
0&
1#
#360000
0#
#370000
1#
#380000
0#
#390000
1#
#400000
0#
#410000
1#
#420000
0#
#430000
1#
#440000
0#
#450000
1#
#460000
0#
#470000
1#
#480000
0#
#490000
1#
#500000
0#
b1001 ,
#510000
1&
b1001 %
b1001 (
1#
#520000
0#
#530000
0&
1#
#540000
0#
#550000
1#
#560000
0#
#570000
1#
#580000
0#
#590000
1#
#600000
0#
#610000
1#
#620000
0#
#630000
1#
#640000
0#
#650000
1#
#660000
0#
#670000
1#
#680000
0#
#690000
1#
#700000
0#
#710000
1#
#720000
0#
#730000
1&
b1010 %
b1010 (
1#
b1010 ,
#740000
0#
#750000
0&
1#
#760000
0#
#770000
1#
#780000
0#
#790000
1#
#800000
0#
#810000
1#
#820000
0#
#830000
1#
#840000
0#
#850000
b1111 ,
1#
#860000
0#
#870000
1&
b1111 %
b1111 (
1#
#880000
0#
#890000
0&
1#
#900000
0#
#910000
1#
#920000
0#
#930000
1#
#940000
0#
#950000
1#
#960000
0#
#970000
1#
#980000
0#
#990000
1#
#1000000
0#
#1010000
1#
#1020000
0#
#1030000
1#
#1040000
0#
#1050000
1#
#1060000
0#
#1070000
1#
#1080000
0#
#1090000
b0 )
b0 +
1#
0'
#1100000
0#
#1110000
1#
#1120000
0#
#1130000
1#
#1140000
0#
b1 ,
1'
#1150000
b1 )
b1 +
1&
b1 %
b1 (
1#
#1160000
0#
#1170000
0&
1#
#1180000
0#
#1190000
1#
#1200000
0#
#1210000
1#
#1220000
0#
#1230000
1#
#1240000
0#
#1250000
1#
#1260000
0#
#1270000
b10 ,
1#
#1280000
0#
#1290000
b10 )
b1100 +
1&
b10 %
b10 (
1#
#1300000
0#
#1310000
0&
1#
#1320000
0#
#1330000
1#
#1340000
0#
#1350000
1#
#1360000
0#
#1370000
1#
#1380000
0#
#1390000
1#
#1400000
0#
#1410000
b1000 ,
1#
#1420000
0#
#1430000
1"
b10000000 !
b10000000 *
b11 )
b10000000 +
1&
b1000 %
b1000 (
1#
#1440000
0#
#1450000
0"
0&
1#
